Metadata-Version: 2.1
Name: reaxfit
Version: 0.2.10
Summary: parameter fitting for ReaxFF
Home-page: https://github.com/ykanematsu/reaxfit
Author: ykanematsu
License: MIT
License-File: LICENSE
